pipman/__init__.py
pipman/pipman.py
pipman-0.0.3.dist-info/DESCRIPTION.rst
pipman-0.0.3.dist-info/METADATA
pipman-0.0.3.dist-info/RECORD
pipman-0.0.3.dist-info/WHEEL
pipman-0.0.3.dist-info/entry_points.txt
pipman-0.0.3.dist-info/metadata.json
pipman-0.0.3.dist-info/top_level.txt
