Metadata-Version: 2.0
Name: pipman
Version: 0.0.3
Summary: A wrapper around pip that provides additional/useful features not included in pip itself
Home-page: https://github.com/Kentoseth/pipman
Author: Kentoseth
Author-email: kentoseth@devcroo.com
License: GNU General Public License v3
Keywords: cli pip wrapper extra-features
Platform: UNKNOWN
Classifier: Programming Language :: Python :: 3.6
Classifier: Development Status :: 3 - Alpha
Classifier: Environment :: Console
Classifier: License :: OSI Approved :: GNU General Public License v3 or later (GPLv3+)
Classifier: Natural Language :: English
Classifier: Intended Audience :: Developers
Classifier: Intended Audience :: System Administrators
Classifier: Operating System :: POSIX :: Linux
Classifier: Topic :: System :: Installation/Setup
Classifier: Topic :: System :: Software Distribution
Classifier: Topic :: Software Development :: Build Tools
Classifier: Topic :: Software Development :: Libraries :: Python Modules
Requires-Dist: argh
Requires-Dist: colorama
Provides-Extra: dev
Provides-Extra: docs
Provides-Extra: testing
